{
  "a number": " x ",
  " x ": " x ",
  "original number": " x ",
  "x": " x ",
  "add": " + ",
  " + ": " + ",
  "addition": " + ",
  "summation": " + ",
  "sum": " + ",
  "altogether": " + ",
  "more": " + ",
  "plus": " + ",
  "subtract": " - ",
  " - ": " - ",
  "subtraction": " - ",
  "less": " - ",
  "difference": " - ",
  "minus": " - ",
  "multiply": " * ",
  " * ": " * ",
  "multiplication": " * ",
  "times": " * ",
  "split": " / ",
  " / ": " / ",
  "division": " / ",
  "divide": " / ",
  "match": " = ",
  " = ": " = ",
  "matches": " = ",
  "equals": " = ",
  "equality": " = ",
  "equal": " = ",
  "is": " = "
}